<?xml version = '1.0' encoding = 'UTF-8'?>
<Relation class="oracle.dbtools.crest.model.design.logical.Relation" name="Relation_5" directorySegmentName="seg_0" id="AF98EE44-0CBD-849C-0EEF-8084B9B9F9BC">
<createdBy>vanbockr20</createdBy>
<createdTime>2022-10-27 12:21:31 UTC</createdTime>
<ownerDesignName>ER-Modell</ownerDesignName>
<engineerTo>
<item key="DCCD9115-7623-CDF6-302A-529A86F17352" value="true"/>
</engineerTo>
<sourcePk>9E8F4B5A-5283-2DDE-E970-7B94EB51EC5A</sourcePk>
<targetPk>51220CEA-8C4C-7303-7752-742433583921</targetPk>
<identifying>false</identifying>
<optionalSource>false</optionalSource>
<optionalTarget>true</optionalTarget>
<sourceCardinality>*</sourceCardinality>
<sourceEntity>D39FA2FA-7915-E88F-4260-93495B622ED1</sourceEntity>
<targetCardinalityString>1</targetCardinalityString>
<targetEntity>B48A8646-D6BA-92FD-AE8E-B0D7FA0CF8F1</targetEntity>
<transferable>true</transferable>
<deleteRule>NO ACTION</deleteRule>
</Relation>